constants.py
protocolplus.py
specs.py
protocolplus-0.2.dist-info/LICENSE.txt
protocolplus-0.2.dist-info/METADATA
protocolplus-0.2.dist-info/WHEEL
protocolplus-0.2.dist-info/entry_points.txt
protocolplus-0.2.dist-info/top_level.txt
protocolplus-0.2.dist-info/RECORD
